setuptools_git_versioning.py
lcdp_setuptools_git_versioning-1.3.7.dist-info/LICENSE
lcdp_setuptools_git_versioning-1.3.7.dist-info/METADATA
lcdp_setuptools_git_versioning-1.3.7.dist-info/WHEEL
lcdp_setuptools_git_versioning-1.3.7.dist-info/entry_points.txt
lcdp_setuptools_git_versioning-1.3.7.dist-info/top_level.txt
lcdp_setuptools_git_versioning-1.3.7.dist-info/RECORD
