Metadata-Version: 2.1
Name: lcdp-setuptools-git-versioning
Version: 1.3.7
Summary: Use git repo data for building a version number according PEP-440
Home-page: https://github.com/LeComptoirDesPharmacies/setuptools-git-versioning
Author: Camas
Author-email: camas@hotmail.co.uk
Maintainer: dolfinus
Maintainer-email: martinov.m.s.8@gmail.com
License: MIT
Keywords: setuptools git version-control
Platform: UNKNOWN
Classifier: Framework :: Setuptools Plugin
Classifier: Intended Audience :: Developers
Classifier: Programming Language :: Python :: 2
Classifier: Programming Language :: Python :: 2.7
Classifier: Programming Language :: Python :: 3
Classifier: Programming Language :: Python :: 3.3
Classifier: Programming Language :: Python :: 3.4
Classifier: Programming Language :: Python :: 3.5
Classifier: Programming Language :: Python :: 3.6
Classifier: Programming Language :: Python :: 3.7
Classifier: Programming Language :: Python :: 3.8
Classifier: Programming Language :: Python :: 3.9
Classifier: License :: OSI Approved :: MIT License
Classifier: Operating System :: OS Independent
Requires-Python: >=2.7,!=3.1,!=3.2
Requires-Dist: six (>=1.13.0)
Requires-Dist: setuptools (<45.0) ; python_version < "3"
Requires-Dist: typing ; python_version < "3"
Requires-Dist: setuptools (<=39.2) ; python_version == "3.3"
Requires-Dist: typing (<3.7,>=3.6) ; python_version == "3.3"
Requires-Dist: setuptools (<=39.2) ; python_version == "3.4"
Requires-Dist: typing (<3.7,>=3.6) ; python_version == "3.4"
Requires-Dist: setuptools ; python_version >= "3.5"
